trust/trust_free.cpython-311-darwin.so
trust/__init__.py
trust_free-2.1.4.dist-info/RECORD
trust_free-2.1.4.dist-info/WHEEL
trust_free-2.1.4.dist-info/top_level.txt
trust_free-2.1.4.dist-info/METADATA
trust_free-2.1.4.dist-info/licenses/LICENSE.txt
