Metadata-Version: 2.4
Name: trust-free
Version: 2.1.4
Summary: TRUST - Decision Trees with Lasso Leaves and Random Forest accuracy
Home-page: https://adc-trust-ai.github.io/trust/
Author: Albert Dorador Chalar
Maintainer: TRUST Team
Maintainer-email: trustalgorithm.dev@gmail.com
License: Proprietary - Permissive Binary Only
Project-URL: Repository, https://github.com/adc-trust-ai/trust-free
Project-URL: Documentation, https://github.com/adc-trust-ai/trust-free/blob/main/MANUAL.md
Project-URL: Issue Tracker, https://github.com/adc-trust-ai/trust-free/issues
Keywords: machine learning,linear models,decision trees,random forest,regression,interpretable ml,explainable ai,ai safety,compliance
Classifier: Programming Language :: Python :: 3
Classifier: Programming Language :: Python :: 3.11
Classifier: Programming Language :: Python :: 3.12
Classifier: License :: Other/Proprietary License
Classifier: Operating System :: OS Independent
Classifier: Topic :: Scientific/Engineering :: Artificial Intelligence
Classifier: Topic :: Scientific/Engineering :: Mathematics
Classifier: Topic :: Software Development :: Libraries :: Python Modules
Classifier: Topic :: Office/Business :: Financial
Classifier: Intended Audience :: Financial and Insurance Industry
Classifier: Intended Audience :: Healthcare Industry
Classifier: Intended Audience :: Science/Research
Classifier: Intended Audience :: Information Technology
Classifier: Intended Audience :: Education
Classifier: Natural Language :: English
Requires-Python: >=3.11,<3.13
License-File: LICENSE.txt
Requires-Dist: ipython>=9.4.0
Requires-Dist: joblib>=1.5.1
Requires-Dist: matplotlib>=3.10.5
Requires-Dist: numpy<2.0.0,>=1.26.4
Requires-Dist: pandas>=2.3.2
Requires-Dist: plotly>=6.3.1
Requires-Dist: PyALE>=1.2.0
Requires-Dist: pydot>=4.0.1
Requires-Dist: scikit-learn>=1.7.1
Requires-Dist: scipy>=1.16.1
Requires-Dist: shap>=0.48.0
Requires-Dist: statsmodels>=0.14.5
Dynamic: author
Dynamic: classifier
Dynamic: description
Dynamic: description-content-type
Dynamic: home-page
Dynamic: keywords
Dynamic: license
Dynamic: license-file
Dynamic: maintainer
Dynamic: maintainer-email
Dynamic: project-url
Dynamic: requires-dist
Dynamic: requires-python
Dynamic: summary
